ray_ease/__init__.py
ray_ease/__version__.py
ray_ease/core.py
ray_ease/remote_as_local.py
ray_ease-0.2.7.dist-info/LICENSE
ray_ease-0.2.7.dist-info/METADATA
ray_ease-0.2.7.dist-info/WHEEL
ray_ease-0.2.7.dist-info/top_level.txt
ray_ease-0.2.7.dist-info/RECORD
