Metadata-Version: 2.1
Name: ray-ease
Version: 0.2.7
Summary: Switch from serial to parallel computing without requiring any code modifications.
Home-page: https://github.com/aelskens/ray-ease
Author: Arthur Elskens
Author-email: arthurelsk@gmail.com
License: MIT
Project-URL: GitHub, https://github.com/aelskens/ray-ease
Project-URL: Tracker, https://github.com/aelskens/ray-ease/issues
Classifier: License :: OSI Approved :: MIT License
Classifier: Programming Language :: Python
Classifier: Programming Language :: Python :: 3
Classifier: Programming Language :: Python :: 3.8
Classifier: Programming Language :: Python :: Implementation :: CPython
Classifier: Programming Language :: Python :: Implementation :: PyPy
Requires-Python: >=3.8
License-File: LICENSE
Requires-Dist: ray[default] >=2.6.2
Requires-Dist: tqdm >=4.66.1
